{
  "orders": [
    {
      "id": "dc9e",
      "name": "jake",
      "email": "jake@email.com",
      "phone": 7854896589,
      "quantity": 1,
      "address": {
        "street": "evan street",
        "city": "balceno",
        "state": "yuan",
        "zipCode": "24325"
      },
      "product": {
        "id": "2",
        "name": "Low-Fat Milk",
        "description": "Nutritious low-fat milk, perfect for everyday use",
        "category": "Milk",
        "imageUrl": "assets/images/low-fat-milk.jpg",
        "price": 2.99
      }
    },
    {
      "id": "efdc",
      "name": "mike",
      "email": "mike@email.com",
      "phone": 8965874589,
      "quantity": 1,
      "address": {
        "street": "Hill road",
        "city": "Incalna",
        "state": "Monvoto",
        "zipCode": "454353"
      },
      "product": {
        "id": "6",
        "name": "Swiss Cheese",
        "description": "Mild, nutty Swiss cheese with a distinctive hole pattern",
        "category": "Cheese",
        "imageUrl": "assets/images/swiss-cheese.jpg",
        "price": 6.49
      }
    },
    {
      "id": "2961",
      "name": "Lionas",
      "email": "lionas@kmail.to",
      "phone": 8041256004,
      "quantity": 1,
      "address": {
        "street": "Toren north",
        "city": "Halbon",
        "state": "Quanch",
        "zipCode": "200045"
      },
      "product": {
        "id": "4",
        "name": "Cheddar Cheese",
        "description": "Sharp, flavorful cheddar cheese made from the finest milk",
        "category": "Cheese",
        "imageUrl": "assets/images/cheddar-cheese.jpg",
        "price": 5.99
      }
    },
    {
      "id": "67a0",
      "name": "James",
      "email": "james@hotmail.com",
      "phone": 9012543008,
      "quantity": 1,
      "address": {
        "street": "Grina venu",
        "city": "Campala",
        "state": "Toronto",
        "zipCode": "700024"
      },
      "product": {
        "id": "9",
        "name": "Organic Ghee",
        "description": "Clarified butter with a nutty flavor, great for high-heat cooking",
        "category": "Butter",
        "imageUrl": "assets/images/organic-ghee.jpg",
        "price": 9.99
      }
    },
    {
      "id": "9fb2",
      "name": "suraj rao",
      "email": "suraj@email",
      "phone": 7854896589,
      "quantity": 100,
      "address": {
        "street": "nagar",
        "city": "ongole",
        "state": "Andhra Pradesh",
        "zipCode": "120212"
      },
      "product": {
        "id": "3",
        "name": "Organic Skim Milk",
        "description": "Organic, fat-free milk for a healthier lifestyle",
        "category": "Milk",
        "imageUrl": "assets/images/skim-milk.jpg",
        "price": 4.49
      }
    },
    {
      "id": "b626",
      "name": "raju",
      "email": "raju@gmail.com",
      "phone": 8965896547,
      "quantity": 1,
      "address": {
        "street": "gandhi nagar",
        "city": "ongole",
        "state": "AP",
        "zipCode": "523001"
      },
      "product": {
        "id": "2",
        "name": "Low-Fat Milk",
        "description": "Nutritious low-fat milk, perfect for everyday use",
        "category": "Milk",
        "imageUrl": "assets/images/low-fat-milk.jpg",
        "price": 2.99
      }
    }
  ]
}